speedpycom/__init__.py
speedpycom/settings.py
speedpycom/storages.py
speedpycom-0.1.16.dist-info/WHEEL
speedpycom-0.1.16.dist-info/METADATA
speedpycom-0.1.16.dist-info/RECORD
